{
  "version": "1.0.0",
  "build_number": 1,
  "download_url": "https://doctorshero.com/downloads/DoctorsHero_Core_Setup_v1.0.0.exe",
  "release_date": "2025-11-30",
  "release_notes": "Initial release of DoctorsHero Core",
  "features": [
    "Professional prescription management",
    "Medicine database with autocomplete",
    "Custom dosage drawer for all medicine types",
    "Interval and duration support",
    "PDF generation with custom layouts",
    "Print settings customization"
  ],
  "minimum_version": "1.0.0",
  "force_update": false,
  "changelog": {
    "1.0.0": [
      "Initial release",
      "Core prescription features",
      "Windows desktop support"
    ]
  }
}
